{
  "_meta": {
    "fetched_at": "2026-02-26T03:10:27Z",
    "source": "github_rest",
    "endpoint": "/repos/{owner}/{repo}/commits",
    "owner": "ros-visualization",
    "repo": "rqt_graph"
  },
  "data": [
    {
      "sha": "1868c6aa4794c5fe06875b9956830826bd4f5bb9",
      "author": "Alejandro Hernandez Cordero",
      "author_login": "ahcorde",
      "date": "2025-07-25T10:27:54Z",
      "message": "1.8.1"
    },
    {
      "sha": "40c89772e7df17d60da49f4b94971c092dccee56",
      "author": "Alejandro Hernandez Cordero",
      "author_login": "ahcorde",
      "date": "2025-07-25T10:27:51Z",
      "message": "Changelog\n\nSigned-off-by: Alejandro Hernandez Cordero <ahcorde@gmail.com>"
    },
    {
      "sha": "09f2debcad91d673f48be0fd23083677f78347c3",
      "author": "Jonas Otto",
      "author_login": "ottojo",
      "date": "2025-07-24T06:57:27Z",
      "message": "add warning for type incompatibilities (#105)\n\nCo-authored-by: Alejandro Hernández Cordero <ahcorde@gmail.com>"
    },
    {
      "sha": "4e6a9b7a758e2e145523d8a1ae030b5e48d60005",
      "author": "Chris Lalancette",
      "author_login": "clalancette",
      "date": "2025-07-23T19:22:39Z",
      "message": "Remove rqt_graph script. (#66)\n\nInstead, only install the console script, which means it will\nwork on both Unix and Windows.\n\nSigned-off-by: Chris Lalancette <clalancette@openrobotics.org>\nCo-authored-by: Alejandro Hernandez Cordero <ahcorde@gmail.com>"
    },
    {
      "sha": "e72fdcb4a2c26781cc25415549f73ecd5f1c7419",
      "author": "mosfet80",
      "author_login": "mosfet80",
      "date": "2025-07-23T19:22:01Z",
      "message": "fix setuptools deprecations (#107)"
    },
    {
      "sha": "940db03dac9f9b7eb92e7f62c0405886b4a65825",
      "author": "Scott K Logan",
      "author_login": "cottsay",
      "date": "2025-04-28T21:48:19Z",
      "message": "1.8.0"
    },
    {
      "sha": "f66873a44f68dac6b8cc4bb7356e84d75c2bd22f",
      "author": "Yadunund",
      "author_login": "Yadunund",
      "date": "2025-02-02T20:12:18Z",
      "message": "1.7.0"
    },
    {
      "sha": "6c484d920ef94e6acd724b508b2afc3e9a28bf01",
      "author": "Yadunund",
      "author_login": "Yadunund",
      "date": "2025-02-02T20:12:00Z",
      "message": "Update changelogs\n\nSigned-off-by: Yadunund <yadunund@gmail.com>"
    },
    {
      "sha": "d1b52f804da79f4e07c19d35b82edcdbc318bbd9",
      "author": "Chris Lalancette",
      "author_login": "clalancette",
      "date": "2024-12-31T13:49:09Z",
      "message": "Add in standard tests. (#104)\n\nSigned-off-by: Chris Lalancette <clalancette@gmail.com>"
    },
    {
      "sha": "90e5f729a4b903105d0f8ecc11cced1061b63975",
      "author": "Alejandro Hernández Cordero",
      "author_login": "ahcorde",
      "date": "2024-12-02T17:01:20Z",
      "message": "Remove CODEOWNERS (#102)\n\nSigned-off-by: Alejandro Hernández Cordero <ahcorde@gmail.com>"
    },
    {
      "sha": "cd40aeacc11f3674730b3530eb57a122832517b6",
      "author": "Chris Lalancette",
      "author_login": "clalancette",
      "date": "2024-06-17T15:04:44Z",
      "message": "1.6.1"
    },
    {
      "sha": "542f93843e3ec79ea9aa05397cde868067248fc5",
      "author": "Chris Lalancette",
      "author_login": "clalancette",
      "date": "2024-06-17T15:04:35Z",
      "message": "Changelog.\n\nSigned-off-by: Chris Lalancette <clalancette@gmail.com>"
    },
    {
      "sha": "a5a903c6f080b976b10dc5e32b21945f9ce1db2b",
      "author": "Alejandro Hernández Cordero",
      "author_login": "ahcorde",
      "date": "2024-05-13T17:28:23Z",
      "message": "Fixed fit_in_view icon button (#95)\n\nSigned-off-by: Alejandro Hernández Cordero <ahcorde@gmail.com>"
    },
    {
      "sha": "c7f00a91666d5da2629bb2cdaad1df0767041409",
      "author": "Marco A. Gutierrez",
      "author_login": "marcoag",
      "date": "2024-04-26T12:31:36Z",
      "message": "1.6.0"
    },
    {
      "sha": "914281ae04a26046e0362feb9cd3b3d4e2ae8b8b",
      "author": "Marco A. Gutierrez",
      "author_login": "marcoag",
      "date": "2024-04-26T12:31:33Z",
      "message": "Changelog.\n\nSigned-off-by: Marco A. Gutierrez <marcogg@marcogg.com>"
    },
    {
      "sha": "ede606293b336bff8fc0bcbb865dbb159e43a049",
      "author": "Marco A. Gutierrez",
      "author_login": "marcoag",
      "date": "2024-04-16T09:38:03Z",
      "message": "1.5.3\n\nSigned-off-by: Marco A. Gutierrez <marcogg@marcogg.com>"
    },
    {
      "sha": "010029329f4a4522d91fbfd7dd94010535f0be6e",
      "author": "Marco A. Gutierrez",
      "author_login": "marcoag",
      "date": "2024-04-16T09:37:39Z",
      "message": "Changelog.\n\nSigned-off-by: Marco A. Gutierrez <marcogg@marcogg.com>"
    },
    {
      "sha": "7b45f8a6e86e0d7d03a25d6a585ab4394f7d228e",
      "author": "Michael Jeronimo",
      "author_login": null,
      "date": "2024-02-08T18:49:53Z",
      "message": "Update maintainer list in package.xml files (#92)\n\n* Update maintainer list in package.xml files\r\n\r\n* Switch maintainer to me.\r\n\r\nSigned-off-by: Michael Jeronimo <michael.jeronimo@openrobotics.org>\r\nSigned-off-by: Chris Lalancette <clalancette@gmail.com>"
    },
    {
      "sha": "553901ee0ab695391bb84042f9cfc00e55ceb929",
      "author": "Chris Lalancette",
      "author_login": "clalancette",
      "date": "2024-02-07T14:29:48Z",
      "message": "1.5.2"
    },
    {
      "sha": "39dd1edf917f1941ad7099a1fed9b32ef2b8ce6d",
      "author": "Chris Lalancette",
      "author_login": "clalancette",
      "date": "2024-02-07T14:29:40Z",
      "message": "Changelog.\n\nSigned-off-by: Chris Lalancette <clalancette@gmail.com>"
    },
    {
      "sha": "b8db63735d19fb7270d095bb50b1d0d8417595b0",
      "author": "Chris Lalancette",
      "author_login": "clalancette",
      "date": "2024-02-06T20:22:05Z",
      "message": "Add a test dependency on python3-pytest. (#91)\n\nIt is required to run the tests that are here.\r\n\r\nSigned-off-by: Chris Lalancette <clalancette@gmail.com>"
    },
    {
      "sha": "41b2c10910f673813aa8033586f45e93616eac78",
      "author": "Yadunund",
      "author_login": "Yadunund",
      "date": "2023-05-11T08:54:14Z",
      "message": "1.5.1"
    },
    {
      "sha": "025580b2e52c383b9fd1cb20f1f0caf9e2ef2301",
      "author": "Yadunund",
      "author_login": "Yadunund",
      "date": "2023-05-11T08:53:41Z",
      "message": "Changelog\n\nSigned-off-by: Yadunund <yadunund@openrobotics.org>"
    },
    {
      "sha": "b117817d4ed72e1b9166c45fb395997e6c3f76f6",
      "author": "Yadu",
      "author_login": "Yadunund",
      "date": "2023-05-08T19:24:10Z",
      "message": "Refresh rosgraph when params checkbox is clicked (#86)\n\nSigned-off-by: Yadunund <yadunund@openrobotics.org>"
    },
    {
      "sha": "9f722ecced78432e8df16c082ecd7abfb4f3cbe5",
      "author": "Chris Lalancette",
      "author_login": "clalancette",
      "date": "2023-04-28T16:31:38Z",
      "message": "1.5.0"
    },
    {
      "sha": "f45d2d4d982e9280c57f414a7db867a80c94b26b",
      "author": "Chris Lalancette",
      "author_login": "clalancette",
      "date": "2023-04-28T16:31:34Z",
      "message": "Changelog\n\nSigned-off-by: Chris Lalancette <clalancette@gmail.com>"
    },
    {
      "sha": "c2d67de430829a5956fe1b3aed5aaf697d7534c4",
      "author": "Chris Lalancette",
      "author_login": "clalancette",
      "date": "2023-02-14T16:21:40Z",
      "message": "1.4.1"
    },
    {
      "sha": "943b8eb476690187c35965fe9bc52ce03ebe3e95",
      "author": "Chris Lalancette",
      "author_login": "clalancette",
      "date": "2023-02-14T16:21:35Z",
      "message": "Changelog.\n\nSigned-off-by: Chris Lalancette <clalancette@gmail.com>"
    },
    {
      "sha": "550451bee418b3e946dba7456a2ddea10cd1a05e",
      "author": "Audrow Nash",
      "author_login": "audrow",
      "date": "2022-11-15T22:30:03Z",
      "message": "[rolling] Update maintainers - 2022-11-07 (#83)"
    },
    {
      "sha": "41bd83a96cdf2182d7bdf0ea5c2b973b0c48ddd6",
      "author": "Chris Lalancette",
      "author_login": "clalancette",
      "date": "2022-09-14T01:35:15Z",
      "message": "Remove the automatic mirroring of 'rolling' to 'galactic-devel'. (#81)\n\nThis isn't what we actually want for this repository.\r\n\r\nSigned-off-by: Chris Lalancette <clalancette@openrobotics.org>"
    },
    {
      "sha": "23b19d0b3acc93e8316bc177f1d42b41ab5adb2c",
      "author": "Chris Lalancette",
      "author_login": "clalancette",
      "date": "2022-09-13T23:01:29Z",
      "message": "1.4.0"
    },
    {
      "sha": "98f82f2af095e8ef29ca898ab1a8f67f8329a6d1",
      "author": "Chris Lalancette",
      "author_login": "clalancette",
      "date": "2022-09-13T23:00:51Z",
      "message": "Changelog.\n\nSigned-off-by: Chris Lalancette <clalancette@openrobotics.org>"
    },
    {
      "sha": "052f0a4f9aa549216e57c086bb85290c4b4723d2",
      "author": "David V. Lu!!",
      "author_login": "DLu",
      "date": "2022-08-10T15:33:53Z",
      "message": "Minor cleanup (#80)"
    },
    {
      "sha": "776602caab8e1d2f408748d9012af71ce2a3ce4e",
      "author": "Audrow Nash",
      "author_login": "paudrow",
      "date": "2022-06-28T14:16:16Z",
      "message": "Mirror rolling to galactic-devel"
    },
    {
      "sha": "cafbf234686e2ac361f90175c4cc5fc81d95568d",
      "author": "mergify[bot]",
      "author_login": "mergify[bot]",
      "date": "2022-06-27T19:15:11Z",
      "message": "graph load/save into DOT file corrections for py3 (#78)\n\n(cherry picked from commit 0f24f498bbfd58854b1d46baff85e246f0782188)\r\n\r\nCo-authored-by: skudryas <skudryas@skudryas.ru>"
    },
    {
      "sha": "92b9278a1d2a2d7eabc115bc5927afac803b066a",
      "author": "Jacob Perron",
      "author_login": "jacobperron",
      "date": "2022-01-14T17:57:27Z",
      "message": "1.2.1"
    },
    {
      "sha": "5baa7c0d1da42cae5059a4dae4244af2dc4971b2",
      "author": "David V. Lu!!",
      "author_login": "DLu",
      "date": "2021-10-05T14:55:29Z",
      "message": "Fix quiet filtering for node_topic graphs (#70)\n\nSigned-off-by: David V. Lu <davidvlu@gmail.com>"
    },
    {
      "sha": "27f72871fb5114f0e0bc23a2e2cf2c52a21fd2a8",
      "author": "Ivan Santiago Paunovic",
      "author_login": "ivanpauno",
      "date": "2021-03-30T18:48:46Z",
      "message": "1.2.0"
    },
    {
      "sha": "e51c5bcff46a74421feef72ac826e78d98a6592e",
      "author": "Ivan Santiago Paunovic",
      "author_login": "ivanpauno",
      "date": "2021-03-30T18:46:03Z",
      "message": "Changelogs\n\nSigned-off-by: Ivan Santiago Paunovic <ivanpauno@ekumenlabs.com>"
    },
    {
      "sha": "bbc611d077d0ca795e4a0a09889b286690bbebce",
      "author": "Ivan Santiago Paunovic",
      "author_login": "ivanpauno",
      "date": "2021-03-30T18:17:07Z",
      "message": "Make topics that have qos incompatibilities red in the graph (#61)\n\nSigned-off-by: Ivan Santiago Paunovic <ivanpauno@ekumenlabs.com>"
    },
    {
      "sha": "010b91d3b50ece3e9fa768f89671350ce903fbdb",
      "author": "Ivan Santiago Paunovic",
      "author_login": "ivanpauno",
      "date": "2021-03-25T13:49:55Z",
      "message": "Add node name, topic name, and endpoint kind to the qos edge tooltip (#60)\n\nSigned-off-by: Ivan Santiago Paunovic <ivanpauno@ekumenlabs.com>"
    },
    {
      "sha": "6d87edcdc6283fda115dc721dad9218e47b0a8e2",
      "author": "Chris Lalancette",
      "author_login": "clalancette",
      "date": "2021-03-18T14:58:13Z",
      "message": "1.1.1"
    },
    {
      "sha": "c3140c5ab745dc8c935302bdfe5e2eb02cb4765b",
      "author": "Chris Lalancette",
      "author_login": "clalancette",
      "date": "2021-03-18T14:58:01Z",
      "message": "Changelog.\n\nSigned-off-by: Chris Lalancette <clalancette@openrobotics.org>"
    },
    {
      "sha": "980dadcfeb3683ad2b12a3626428d4d1fd2127d2",
      "author": "Michael Jeronimo",
      "author_login": null,
      "date": "2020-10-14T19:50:47Z",
      "message": "Update maintainers for ROS2 branches (#55)\n\nSigned-off-by: Michael Jeronimo <michael.jeronimo@openrobotics.org>"
    },
    {
      "sha": "0f8f6606af3d14643b23d53595f2b3be7c66e8da",
      "author": "Dirk Thomas",
      "author_login": "dirk-thomas",
      "date": "2020-09-23T20:13:35Z",
      "message": "1.1.0"
    },
    {
      "sha": "893487778b5a9a4e5f18fecb55565bee920b9ef4",
      "author": "Dirk Thomas",
      "author_login": "dirk-thomas",
      "date": "2020-09-23T20:13:22Z",
      "message": "update changelog"
    },
    {
      "sha": "11b57e7d8a5aff2d17d717feff9401e3a6d17172",
      "author": "Dirk Thomas",
      "author_login": "dirk-thomas",
      "date": "2020-09-23T20:11:50Z",
      "message": "add edge tooltip with QoS of publishers and subscribers (#53)\n\n* add edge tooltip with QoS of publishers and subscribers\r\n\r\nSigned-off-by: Dirk Thomas <dirk-thomas@users.noreply.github.com>\r\n\r\n* skip some values\r\n\r\nSigned-off-by: Dirk Thomas <dirk-thomas@users.noreply.github.com>\r\n\r\n* collect QoS from all pubs/subs of a topic, render parallel edges for different QoS\r\n\r\nSigned-off-by: Dirk Thomas <dirk-thomas@users.noreply.github.com>"
    },
    {
      "sha": "874d7927cea0bfe721511ec403edd572e4363452",
      "author": "Dirk Thomas",
      "author_login": "dirk-thomas",
      "date": "2020-09-18T21:17:07Z",
      "message": "1.0.5"
    },
    {
      "sha": "3a0b8ed7968dfb1c9361451014222aa669038cb9",
      "author": "Dirk Thomas",
      "author_login": "dirk-thomas",
      "date": "2020-09-18T21:16:48Z",
      "message": "update changelog"
    },
    {
      "sha": "9bce79ca3ed938551bae5418a9f65a71a01c5bf5",
      "author": "Jacob Perron",
      "author_login": "jacobperron",
      "date": "2020-07-29T19:00:09Z",
      "message": "Install executable rqt_graph (#49)\n\n* Install exectuable rqt_graph\r\n\r\nThis fixes a regression introduced in #42.\r\n\r\nNow the application can be started with 'rqt_graph' or with 'ros2 run'\r\n\r\nSigned-off-by: Jacob Perron <jacob@openrobotics.org>\r\n\r\n* Revert \"Add setup.cfg with script install directories (#42)\"\r\n\r\nThis reverts commit 4139a3957acc0b3e2e8258cca9ddb46f62258190.\r\n\r\n* Install entrypoint to bin/ and executable to lib/rqt_graph/\r\n\r\nSigned-off-by: Jacob Perron <jacob@openrobotics.org>\r\n\r\n* Move script to 'scripts' directory\r\n\r\nSigned-off-by: Jacob Perron <jacob@openrobotics.org>"
    },
    {
      "sha": "4139a3957acc0b3e2e8258cca9ddb46f62258190",
      "author": "Alejandro Hernández Cordero",
      "author_login": "ahcorde",
      "date": "2020-07-13T19:15:06Z",
      "message": "Add setup.cfg with script install directories (#42)\n\nThis fixes an issue running rqt_graph with ros2run on Windows.\r\nros2run expects scripts to be in the lib directory.\r\n\r\nSigned-off-by: ahcorde <ahcorde@gmail.com>"
    },
    {
      "sha": "96690a314ec74d474b679f69e91a29abae185ca3",
      "author": "Chris Lalancette",
      "author_login": "clalancette",
      "date": "2020-06-19T14:55:56Z",
      "message": "Add pytest.ini so local tests don't display warning (#48)\n\nSigned-off-by: Chris Lalancette <clalancette@openrobotics.org>"
    },
    {
      "sha": "22952ef7604ed76f573cfae896c96c435203339a",
      "author": "Dirk Thomas",
      "author_login": "dirk-thomas",
      "date": "2020-01-06T18:43:17Z",
      "message": "1.0.4"
    },
    {
      "sha": "c20d53f3975c72a384edff9a2045f327063e1176",
      "author": "Dirk Thomas",
      "author_login": "dirk-thomas",
      "date": "2020-01-06T18:42:19Z",
      "message": "update changelog"
    },
    {
      "sha": "393edcc9a48fe478ceadf1e80c1387b73badff32",
      "author": "Simon Tegelid",
      "author_login": "simontegelid",
      "date": "2020-01-06T18:25:22Z",
      "message": "Skip removal of non-present tf connections (#40)"
    },
    {
      "sha": "f1f7e969d5c74c7077e26c4bcdb34318907a32c8",
      "author": "Jacob Perron",
      "author_login": "jacobperron",
      "date": "2019-10-24T02:31:57Z",
      "message": "1.0.3"
    },
    {
      "sha": "50afa3f943c5db43f7b24e166c35a4e7d90b2c63",
      "author": "Michel Hidalgo",
      "author_login": "hidmic",
      "date": "2019-10-23T23:01:35Z",
      "message": "Add topic edges for the Nodes Only view mode. (#35)\n\n* Add topic edges for the Nodes Only view mode.\r\n\r\nSigned-off-by: Michel Hidalgo <michel@ekumenlabs.com>\r\n\r\n* split into two lines\r\n\r\n* remove used for extra var\r\n\r\n* fix previous commit splitting lines"
    },
    {
      "sha": "5cf4ad8d2411c993d720255087592a38e9828a75",
      "author": "Dirk Thomas",
      "author_login": "dirk-thomas",
      "date": "2019-10-07T20:14:54Z",
      "message": "follow up of #34"
    },
    {
      "sha": "73c308753fef8e117ddd37a525af2fec4760357c",
      "author": "Xavier BROQUERE",
      "author_login": "xbroquer",
      "date": "2019-10-07T20:11:43Z",
      "message": "Fix node not found during refresh when namespace is not empty (#34)\n\n* Fix node not found during refresh when namespace is not empty\r\n\r\nSigned-off-by: Xavier BROQUERE <xav.broquere@gmail.com>\r\n\r\n* don't change the type of the variable, keep diff minimal"
    },
    {
      "sha": "cd2f2f24e6236ccb77ddba1a798fad214280cee2",
      "author": "Dirk Thomas",
      "author_login": "dirk-thomas",
      "date": "2019-10-03T16:00:38Z",
      "message": "1.0.2"
    },
    {
      "sha": "8caf0117805c8901b74df5201e3b37d37b2fc03b",
      "author": "Dirk Thomas",
      "author_login": "dirk-thomas",
      "date": "2019-10-03T16:00:31Z",
      "message": "update changelog"
    },
    {
      "sha": "b4e479bc3f7c41ab86e94e828f0e3409f30d7ffb",
      "author": "Joshua Whitley",
      "author_login": null,
      "date": "2019-09-06T17:03:17Z",
      "message": "Fix typo that caused a crash when trying to load a dot file. (#31)"
    },
    {
      "sha": "1c57bde3ace6afaa23d40fb61cbcba71edbf5586",
      "author": "Dirk Thomas",
      "author_login": "dirk-thomas",
      "date": "2019-05-29T23:48:25Z",
      "message": "1.0.1"
    },
    {
      "sha": "9c29fe2e23fd2e382cf360138f5826ed7bbab66f",
      "author": "Dirk Thomas",
      "author_login": "dirk-thomas",
      "date": "2019-05-29T18:07:42Z",
      "message": "consider ROS 2 parameter events topic and hidden node convention (#30)"
    },
    {
      "sha": "6ad2755984e084b6a4db92a29fbafbf663816ccb",
      "author": "Dirk Thomas",
      "author_login": "dirk-thomas",
      "date": "2019-02-04T19:40:18Z",
      "message": "1.0.0"
    },
    {
      "sha": "48d14ef8bb4919666e784dd58aee52f96799ffd4",
      "author": "brawner",
      "author_login": "brawner",
      "date": "2019-01-31T17:51:47Z",
      "message": "Porting to ROS2 (#22)"
    },
    {
      "sha": "a6cafa38ce6347d5ee889ae3c23706b6c1c28cfb",
      "author": "brawner",
      "author_login": "brawner",
      "date": "2019-01-11T00:00:42Z",
      "message": "Copying base rosgraph.impl.graph file (#23)"
    },
    {
      "sha": "dbfba09d03ab24aa2d45dbab5855676777c36cab",
      "author": "Mike Lautman",
      "author_login": "mlautman",
      "date": "2018-10-23T16:26:37Z",
      "message": "autopep8 and gitignore (#19)"
    },
    {
      "sha": "b1469aec43126b1b1c7477a9188910772e7e9fba",
      "author": "Martin Günther",
      "author_login": "mintar",
      "date": "2018-09-17T14:49:44Z",
      "message": "Replace str() by unicode() (#17)\n\n* Replace str() by unicode()\r\n\r\nThis fixes the following bug: If the user entered a non-ASCII character\r\ninto one of the filter text boxes (for example, by hitting the 'u umlaut' key on a\r\nGerman keyboard), the application crashed before with the following\r\nerror:\r\n\r\n    Traceback (most recent call last):\r\n      File \"/home/martin/ros/kinetic/rqt_graph/src/rqt_graph/src/rqt_graph/ros_graph.py\", line 69, in splitPath\r\n        path = str(path.split(',')[-1]).lstrip(' ')\r\n    UnicodeEncodeError: 'ascii' codec can't encode character u'\\xfc' in position 16: ordinal not in range(128)\r\n\r\nThis commit fixes that.\r\n\r\n* Check for missing unicode() function (py3)"
    },
    {
      "sha": "d9f85e36a9dcfb76a96449199e88e7e1d4373b9b",
      "author": "Kartik Mohta",
      "author_login": "kartikmohta",
      "date": "2018-08-27T19:49:48Z",
      "message": "Edge class is unhashable so cannot put into a set, use a list instead (#16)"
    },
    {
      "sha": "a2d9c1cf9f05533c6c36b6c1a1b5998bb74fbfef",
      "author": "Dirk Thomas",
      "author_login": "dirk-thomas",
      "date": "2018-05-22T23:03:43Z",
      "message": "0.4.10"
    },
    {
      "sha": "900583b08d2046937ae810a4712a8afe6d59f13d",
      "author": "Dirk Thomas",
      "author_login": "dirk-thomas",
      "date": "2018-05-22T23:03:34Z",
      "message": "update changelog"
    },
    {
      "sha": "e1945ecf7d127e7b061c58c7c5c3e5980df2dbe8",
      "author": "E2",
      "author_login": "EliteMasterEric",
      "date": "2018-05-22T23:02:58Z",
      "message": "Added nested subnamespaces and more options to hide or group topics. (#13)\n\n* Added nested subnamespaces.\r\n\r\nThe \"Group Namespaces\" checkbox has been replaced with a numeric spinner, where the user can specify the desired layers of depth.\r\n\r\n* Moved the Hide section of the toolbar to a new line\r\n\r\n* Grouped topics now display as 3d boxes.\r\n\r\n* Added checkboxes to hide or group tf topics (/tf and /tf_static)\r\n\r\n* Added checkbox to group image topics (/, /compressed, /theora, and /compressedDepth)\r\n\r\n\r\nimage_fix\r\n\r\n* Added a checkbox to hide topics added by ros/dynamic_reconfigure.\r\n\r\nParameter topics include /parameter_descriptions and /parameter_updates.\r\n\r\n* Changed dependency version, removed annoying margins in window\r\n\r\n* Refactored lines to reduce redundancy, and minimize long lines of indent\r\n\r\n* remove version dependency in order to work with Indigo"
    },
    {
      "sha": "90117a0b04c99d1baf4589dc97751fa3487883a4",
      "author": "Dirk Thomas",
      "author_login": "dirk-thomas",
      "date": "2017-07-27T15:04:43Z",
      "message": "0.4.9"
    },
    {
      "sha": "5ca1798cc1a08f2a552f7972515e426aa96f9d10",
      "author": "Dirk Thomas",
      "author_login": "dirk-thomas",
      "date": "2017-07-27T15:04:36Z",
      "message": "update changelog"
    },
    {
      "sha": "16f5b280922fb8ce0f8eefe5b388dc418ad9e92c",
      "author": "Dirk Thomas",
      "author_login": "dirk-thomas",
      "date": "2017-07-10T20:55:40Z",
      "message": "Merge pull request #10 from kartikmohta/fix/python3\n\nFixes for Python3"
    },
    {
      "sha": "21c2c5078d2f81c6130d0ada695112b64c42d962",
      "author": "Kartik Mohta",
      "author_login": "kartikmohta",
      "date": "2017-06-02T00:35:24Z",
      "message": "Fixes for Python3\n\nThe filter method returns an iterator in Python3 instead of a list"
    },
    {
      "sha": "8b3377f5590befb759010b4a56767ede3c1dcc59",
      "author": "Dirk Thomas",
      "author_login": "dirk-thomas",
      "date": "2017-05-23T16:36:31Z",
      "message": "Merge pull request #8 from ros-visualization/fix_namespacing\n\nonly show namespaces if all entities have a common non-empty base path"
    },
    {
      "sha": "32198c4f1ca6e841aab35f079b760a2aa91d725a",
      "author": "Dirk Thomas",
      "author_login": "dirk-thomas",
      "date": "2017-05-22T20:24:38Z",
      "message": "only show namespaces if all entities have a common non-empty base path"
    },
    {
      "sha": "3ad9e5314677ea442b771ff5909b9496028f1d08",
      "author": "Dirk Thomas",
      "author_login": "dirk-thomas",
      "date": "2017-04-24T23:32:12Z",
      "message": "0.4.8"
    },
    {
      "sha": "18586a19a8e014c84bbfdd533c809838786e19b1",
      "author": "Dirk Thomas",
      "author_login": "dirk-thomas",
      "date": "2017-04-24T23:32:07Z",
      "message": "update changelog"
    },
    {
      "sha": "0f75039a188344e482cf599999596a117a1f41bd",
      "author": "Dirk Thomas",
      "author_login": "dirk-thomas",
      "date": "2017-04-24T21:29:24Z",
      "message": "update urls, add myself as maintainer"
    },
    {
      "sha": "3d77bb80bfd8df4b4849f35ec4edfda09e750943",
      "author": "Dirk Thomas",
      "author_login": "dirk-thomas",
      "date": "2017-04-24T18:35:56Z",
      "message": "move package to root of repo"
    },
    {
      "sha": "4c9df440a1ca31f6be9506711b33e82707c0dd3d",
      "author": "Dirk Thomas",
      "author_login": "dirk-thomas",
      "date": "2017-04-24T16:38:38Z",
      "message": "Merge pull request #433 from contradict/scroll_area\n\n[rqt_image_view] Add a scroll area"
    },
    {
      "sha": "6cfdd012d99c593fcf178ee3b81d70268b52c068",
      "author": "Michael Johnson",
      "author_login": "MJohnson459",
      "date": "2017-04-24T16:10:05Z",
      "message": "[rqt_graph] Show bad nodes even if debug (quiet) is set (#448)\n\n* Showing bad nodes even if debug is set to support master only connections (docker)\r\n\r\n* Added hide unreachable checkbox to the rqt_graph GUI"
    },
    {
      "sha": "1d3a6d1ddb2d42ee1923d55b45be67f7ba73bbf6",
      "author": "Dirk Thomas",
      "author_login": "dirk-thomas",
      "date": "2017-03-02T15:59:40Z",
      "message": "0.4.7"
    },
    {
      "sha": "1d15db949a147633d1b3f37f414d25703aa444af",
      "author": "Dirk Thomas",
      "author_login": "dirk-thomas",
      "date": "2017-03-02T15:59:32Z",
      "message": "update changelogs"
    },
    {
      "sha": "be86c6e0cdc45e5bbc2b731ea40d948a3f41b630",
      "author": "Dirk Thomas",
      "author_login": "dirk-thomas",
      "date": "2017-03-02T15:57:48Z",
      "message": "Merge pull request #439 from sosswald/fix-428\n\nFix crash of rqt_graph when enable_statistics == true, fixes #428"
    },
    {
      "sha": "668699bc30fbcfa0b7a7360c80d3a36f3af38d09",
      "author": "Stefan Osswald",
      "author_login": "sosswald",
      "date": "2017-03-02T11:56:51Z",
      "message": "Fix crash of rqt_graph when enable_statistics == true, fixes #428"
    },
    {
      "sha": "c8c68aab95b9f53bacf044bc87a8ca83961cbb3d",
      "author": "Dirk Thomas",
      "author_login": "dirk-thomas",
      "date": "2017-02-27T19:05:37Z",
      "message": "0.4.6"
    },
    {
      "sha": "c8d67c8fe20f95ac06c1f9eb905ce56b54aa584b",
      "author": "Dirk Thomas",
      "author_login": "dirk-thomas",
      "date": "2017-02-27T19:05:28Z",
      "message": "update changelogs"
    },
    {
      "sha": "1c75d99cb40c8912e0aab51ffa24b80428b44878",
      "author": "Dirk Thomas",
      "author_login": "dirk-thomas",
      "date": "2017-02-03T16:18:05Z",
      "message": "0.4.5"
    },
    {
      "sha": "9619dcac58e0383306ee410ff76be1437744a624",
      "author": "Dirk Thomas",
      "author_login": "dirk-thomas",
      "date": "2017-02-03T16:17:49Z",
      "message": "update changelogs"
    },
    {
      "sha": "fb3b53ffa51ad67d533c39bbe1c84fdeb9c963b7",
      "author": "Dirk Thomas",
      "author_login": "dirk-thomas",
      "date": "2017-01-24T23:33:19Z",
      "message": "0.4.4"
    },
    {
      "sha": "9c18d486669e10d08a96229db12f002bcb720701",
      "author": "Dirk Thomas",
      "author_login": "dirk-thomas",
      "date": "2017-01-24T23:33:07Z",
      "message": "update changelogs"
    },
    {
      "sha": "39c4bcd4dcf7c512eae88fef764160759cb5035d",
      "author": "Dirk Thomas",
      "author_login": "dirk-thomas",
      "date": "2017-01-24T22:31:36Z",
      "message": "Merge pull request #419 from arne48/master\n\nCatching unhandled IOError exceptions if connection to rosmaster gets lost"
    },
    {
      "sha": "20270f82dd113866adfd84d843997c42fcc0bdf0",
      "author": "Dirk Thomas",
      "author_login": "dirk-thomas",
      "date": "2017-01-24T21:49:48Z",
      "message": "Merge pull request #421 from ros-visualization/python3_compatible_syntax\n\nuse Python 3 compatible syntax"
    },
    {
      "sha": "198be333d597f57da8fd746b9fca660b82b0e01f",
      "author": "Dirk Thomas",
      "author_login": "dirk-thomas",
      "date": "2017-01-24T20:26:18Z",
      "message": "use Python 3 compatible syntax"
    },
    {
      "sha": "cedd1f11e467157b3bf259a3e830af4e84eb5710",
      "author": "Dirk Thomas",
      "author_login": "dirk-thomas",
      "date": "2016-12-20T17:00:43Z",
      "message": "Merge pull request #406 from jacquelinekay/rqt_reconfigure_save_load\n\nAdd 'save' and 'load' buttons to rqt_reconfigure"
    },
    {
      "sha": "fd43c5871c695ad5f032ec18109745d381ace73a",
      "author": "Dirk Thomas",
      "author_login": "dirk-thomas",
      "date": "2016-12-20T16:56:16Z",
      "message": "Merge pull request #385 from samuelba/feature/smooth-transformation\n\nrqt_image_view: use smooth transformation for image scaling"
    },
    {
      "sha": "6429a774866aa517949476016afe1db551fb8589",
      "author": "Dirk Thomas",
      "author_login": "dirk-thomas",
      "date": "2016-11-02T17:47:19Z",
      "message": "0.4.3"
    },
    {
      "sha": "488b04ce6f851d8dd06a3420daaef8b6d1a52957",
      "author": "Dirk Thomas",
      "author_login": "dirk-thomas",
      "date": "2016-11-02T17:47:03Z",
      "message": "update changelogs"
    },
    {
      "sha": "facda8b48f1800eea3535577bc25d542629cb947",
      "author": "Dirk Thomas",
      "author_login": "dirk-thomas",
      "date": "2016-09-19T17:25:35Z",
      "message": "0.4.2"
    },
    {
      "sha": "ebe0b0bd56863b6838bde20ffebc95bcbc972c2e",
      "author": "Dirk Thomas",
      "author_login": "dirk-thomas",
      "date": "2016-09-19T17:25:27Z",
      "message": "update changelogs"
    },
    {
      "sha": "a9857e7865153e18ba617676e4bc7d911cb9f660",
      "author": "Dirk Thomas",
      "author_login": "dirk-thomas",
      "date": "2016-05-16T20:13:42Z",
      "message": "0.4.1"
    },
    {
      "sha": "1a3a16b3e0b28437355f9af2d8bd63f933c85158",
      "author": "Dirk Thomas",
      "author_login": "dirk-thomas",
      "date": "2016-05-16T20:13:30Z",
      "message": "update changelogs"
    },
    {
      "sha": "c8716727258d8d205287e35f4fbc3399b362af43",
      "author": "Dirk Thomas",
      "author_login": "dirk-thomas",
      "date": "2016-05-12T19:21:14Z",
      "message": "fix mouse wheel delta in Qt 5 (#376)"
    },
    {
      "sha": "82a878b7e1e7f921f1103139cf8fed22aec0d457",
      "author": "Aaron Blasdel",
      "author_login": "ablasdel",
      "date": "2016-04-27T22:53:19Z",
      "message": "Merge pull request #368 from v-lopez/master\n\nrqt_image_view: Adding the possibility to publish mouse events."
    },
    {
      "sha": "ab03bbf06e7a926659cd66d2b3464da48bdb0400",
      "author": "Dirk Thomas",
      "author_login": "dirk-thomas",
      "date": "2016-04-27T22:07:15Z",
      "message": "0.4.0"
    },
    {
      "sha": "b6baf7525094786d263dd74582f131da7570b947",
      "author": "Dirk Thomas",
      "author_login": "dirk-thomas",
      "date": "2016-04-27T22:07:09Z",
      "message": "update changelogs"
    },
    {
      "sha": "5094c069f47307228fd9b2d8d249c0cc7f3d5e93",
      "author": "Dirk Thomas",
      "author_login": "dirk-thomas",
      "date": "2016-04-27T21:57:11Z",
      "message": "Merge pull request #359 from ros-visualization/qt5\n\nadditionally support Qt5"
    },
    {
      "sha": "599480916b33d2908943d9fe9d6d5d81270a4685",
      "author": "Dirk Thomas",
      "author_login": "dirk-thomas",
      "date": "2016-04-25T18:32:30Z",
      "message": "update minimum dependency on python_qt_binding"
    },
    {
      "sha": "c390e5555a4ed0405133e6cfcb74cd3dbd84fee5",
      "author": "Dirk Thomas",
      "author_login": "dirk-thomas",
      "date": "2016-04-19T01:00:15Z",
      "message": "many more imports"
    },
    {
      "sha": "007f08f4489cfbaeb197512ef3ad539b447d0dbe",
      "author": "Aaron Blasdel",
      "author_login": "ablasdel",
      "date": "2016-04-14T20:50:27Z",
      "message": "Merge pull request #362 from reinzor/master\n\nPass y from scene to map_y_to_topic function"
    },
    {
      "sha": "8a73100dd2f32505c2d6c7d16ec1039cf47d75cf",
      "author": "Aaron Blasdel",
      "author_login": "ablasdel",
      "date": "2016-03-09T01:25:01Z",
      "message": "0.3.13"
    },
    {
      "sha": "1f2bec1df3d84ba0ea042ab11dacd2767ec3b9ef",
      "author": "Aaron Blasdel",
      "author_login": "ablasdel",
      "date": "2016-03-09T01:23:59Z",
      "message": "update changelogs"
    },
    {
      "sha": "26613707ef98480a8a5a33836e075e797ab48aed",
      "author": "Dirk Thomas",
      "author_login": "dirk-thomas",
      "date": "2016-02-27T06:42:56Z",
      "message": "Merge pull request #355 from eric-wieser/narrow-graph\n\nRemove repeated prefices from buttons"
    },
    {
      "sha": "3fdd7878f2f935bd0b52ad4fe29ddd0ab79187dc",
      "author": "Eric Wieser",
      "author_login": "eric-wieser",
      "date": "2016-02-27T03:51:12Z",
      "message": "Remove repeated prefices from buttons"
    },
    {
      "sha": "f0aaa3321b8722db600d1c38181a73f561c8ac50",
      "author": "Aaron Blasdel",
      "author_login": "ablasdel",
      "date": "2016-02-23T23:58:16Z",
      "message": "Merge pull request #352 from ros-visualization/rqt_topic_div_zero\n\ncheck for divide by zero and data failures"
    },
    {
      "sha": "53227f92bb28fe845a7dcb7bc6c85e118030160e",
      "author": "Aaron Blasdel",
      "author_login": "ablasdel",
      "date": "2016-02-23T23:57:32Z",
      "message": "Merge pull request #354 from eric-wieser/patch-1\n\nFixes #333"
    },
    {
      "sha": "e4c8505dbe7deb96724974fadd9f52fe712dd94c",
      "author": "Eric Wieser",
      "author_login": "eric-wieser",
      "date": "2016-02-21T20:29:35Z",
      "message": "Fixes #333\n\nPrefix all node and topic names with `n_` and `t_` respectively, to allow dot to distinguish them"
    },
    {
      "sha": "eb13579763519f35baee65e09914ff5afd30d986",
      "author": "Aaron Blasdel",
      "author_login": "ablasdel",
      "date": "2015-07-24T20:51:28Z",
      "message": "0.3.12"
    },
    {
      "sha": "6edf04c96f85475ae8cd13cb4b0de6dfb2028ecc",
      "author": "Aaron Blasdel",
      "author_login": "ablasdel",
      "date": "2015-07-10T15:55:17Z",
      "message": "Merge pull request #326 from ros-visualization/image_view_save_image\n\n[rqt_image_view] add button to save current image to file"
    },
    {
      "sha": "be071b629644400c72bff9d720da4278a10174ba",
      "author": "Scott K Logan",
      "author_login": "cottsay",
      "date": "2015-07-10T03:47:18Z",
      "message": "Merge pull request #319 from cottsay/refresh_button\n\nrqt_reconfigure: add refresh button"
    },
    {
      "sha": "ded4ab2380a77952a0a3c522539fa06a510ae529",
      "author": "Aaron Blasdel",
      "author_login": "ablasdel",
      "date": "2015-07-08T15:57:21Z",
      "message": "Merge pull request #313 from suryaambrose/groovy-devel\n\nrqt_bag : Addition of a step-by-step play"
    },
    {
      "sha": "1661dfec320b0da57c9e3093cd9e4f5a315b80b1",
      "author": "Dirk Thomas",
      "author_login": "dirk-thomas",
      "date": "2015-04-30T18:06:45Z",
      "message": "0.3.11"
    },
    {
      "sha": "1df2719db4294604112abe5d910cebb0ac5b4bd7",
      "author": "Dirk Thomas",
      "author_login": "dirk-thomas",
      "date": "2015-04-30T18:06:33Z",
      "message": "update changelogs"
    },
    {
      "sha": "7a443295fdb1b31fa54872e3125737bfb8331b48",
      "author": "Aaron Blasdel",
      "author_login": "ablasdel",
      "date": "2014-10-23T20:21:58Z",
      "message": "Merge pull request #286 from ablasdel/groovy-devel\n\ninstall rqt_dep script globally."
    },
    {
      "sha": "69d9cae4973b8458397b7224f460ff69ef862ad8",
      "author": "Aaron Blasdel",
      "author_login": "ablasdel",
      "date": "2014-10-16T18:37:37Z",
      "message": "Merge pull request #284 from ablasdel/groovy-devel\n\nfixes #283"
    },
    {
      "sha": "5cd77e647cc163301396016350c83bd8f8d7acc3",
      "author": "Aaron Blasdel",
      "author_login": "ablasdel",
      "date": "2014-10-16T16:05:59Z",
      "message": "possible fix for #283"
    },
    {
      "sha": "b2170b6e5f5412aa6d65f629e2e98a91600ebae5",
      "author": "Dirk Thomas",
      "author_login": "dirk-thomas",
      "date": "2014-10-01T21:37:36Z",
      "message": "0.3.10"
    },
    {
      "sha": "0f598df69d582c9133db2398ed8dbae9bfc1a94a",
      "author": "Dirk Thomas",
      "author_login": "dirk-thomas",
      "date": "2014-10-01T21:37:23Z",
      "message": "update changelogs"
    },
    {
      "sha": "050c34554f40be1cdf3f2317a73a4d14b3485e2c",
      "author": "Aaron Blasdel",
      "author_login": "ablasdel",
      "date": "2014-09-23T23:34:04Z",
      "message": "Merge pull request #280 from trainman419/close_bag_plugin\n\nrqt_bag: Refactor popup management and close callbacks"
    },
    {
      "sha": "66ff864d7ed7f735ff15756942ee571528181507",
      "author": "Aaron Blasdel",
      "author_login": "ablasdel",
      "date": "2014-09-23T23:24:34Z",
      "message": "Merge pull request #279 from trainman419/fix_bag_topic_type\n\nrqt_bag: Fix topic type retrieval for multiple bag files"
    },
    {
      "sha": "55f12769b951deea6a78e55dcc95732ee31c795b",
      "author": "Dirk Thomas",
      "author_login": "dirk-thomas",
      "date": "2014-08-22T17:58:50Z",
      "message": "Merge pull request #273 from mrdanbrooks/rqt_graph_standalone_fix\n\nchange package name to full plugin name in scripts"
    },
    {
      "sha": "8c5b537aa42619eed6b89343b1a06098a35f282a",
      "author": "dan brooks",
      "author_login": "mrdanbrooks",
      "date": "2014-08-19T00:00:57Z",
      "message": "updates package names to full plugin names for scripts"
    },
    {
      "sha": "99b7c6f350fb4d7ebeb36d0f96cf17fbcd9b206c",
      "author": "Aaron Blasdel",
      "author_login": "ablasdel",
      "date": "2014-08-20T18:25:27Z",
      "message": "Merge pull request #272 from ros-visualization/revert-270-rqt_graph_standalone_fix\n\nRevert \"changes partial name to full name to avoid future naming conflic..."
    },
    {
      "sha": "380e8a14a7a882bfd049240a282a728d9c945061",
      "author": "Aaron Blasdel",
      "author_login": "ablasdel",
      "date": "2014-08-20T18:25:12Z",
      "message": "Revert \"changes partial name to full name to avoid future naming conflicts\""
    },
    {
      "sha": "c338febcf3dbea403eb7c58008916947f68394b3",
      "author": "Aaron Blasdel",
      "author_login": "ablasdel",
      "date": "2014-08-20T18:11:51Z",
      "message": "Merge pull request #270 from mrdanbrooks/rqt_graph_standalone_fix\n\nchanges partial name to full name to avoid future naming conflicts"
    },
    {
      "sha": "645b2d96f2bf21cc5d0b191c4a61adf7fdc0a3ed",
      "author": "dan brooks",
      "author_login": "mrdanbrooks",
      "date": "2014-08-19T20:25:31Z",
      "message": "Merge remote-tracking branch 'other/groovy-devel' into rqt_graph_standalone_fix\n\nConflicts:\n\trqt_top/scripts/rqt_top"
    },
    {
      "sha": "804afa9ec921d24a6d96ebc7ae4ca224070f9281",
      "author": "dan brooks",
      "author_login": "mrdanbrooks",
      "date": "2014-08-19T00:00:57Z",
      "message": "updates plugin scripts to use full name to avoid future naming collisions"
    },
    {
      "sha": "6b0d2543f8c7c92cbede1fbd6b33097690279432",
      "author": "Dirk Thomas",
      "author_login": "dirk-thomas",
      "date": "2014-08-18T18:36:12Z",
      "message": "0.3.9"
    },
    {
      "sha": "02f09d80bee4d035fad52fa80b9b07c7a2c73263",
      "author": "Dirk Thomas",
      "author_login": "dirk-thomas",
      "date": "2014-08-18T18:36:02Z",
      "message": "update changelogs"
    },
    {
      "sha": "214a0e6ad76cca0fdf38f0d01abd144e7c00d877",
      "author": "Aaron Blasdel",
      "author_login": "ablasdel",
      "date": "2014-08-11T17:44:31Z",
      "message": "Merge pull request #262 from trainman419/fix_261\n\nHandle variable-sized arrays. Fixes #261"
    },
    {
      "sha": "9c299836565a29551805de4786dd776650f92e77",
      "author": "Aaron Blasdel",
      "author_login": "ablasdel",
      "date": "2014-08-11T17:14:40Z",
      "message": "Merge pull request #268 from ablasdel/groovy-devel\n\nfixes #266 : nodes are now allowed to create namespaces"
    },
    {
      "sha": "f05ce07393894af0afd837e7cebf8cbe8f399362",
      "author": "Aaron Blasdel",
      "author_login": "ablasdel",
      "date": "2014-08-08T22:34:46Z",
      "message": "fixes #266 : nodes are now allowed to create namespaces"
    },
    {
      "sha": "9051ee765bf078acf3df38e1d3c8a62442de850a",
      "author": "Dirk Thomas",
      "author_login": "dirk-thomas",
      "date": "2014-07-18T18:28:42Z",
      "message": "update / remove outdated email addresses"
    },
    {
      "sha": "62c22b5bee25a98bf0996282df7bcb4b5ba614b7",
      "author": "Dirk Thomas",
      "author_login": "dirk-thomas",
      "date": "2014-07-15T17:11:45Z",
      "message": "0.3.8"
    },
    {
      "sha": "dd956fcde037011822a4965758a140d04dd9623f",
      "author": "Dirk Thomas",
      "author_login": "dirk-thomas",
      "date": "2014-07-15T17:11:31Z",
      "message": "update changelogs"
    },
    {
      "sha": "5399ad5aa1f262937cdc947615b511cbb5cabacd",
      "author": "Dirk Thomas",
      "author_login": "dirk-thomas",
      "date": "2014-07-11T07:09:29Z",
      "message": "0.3.7"
    },
    {
      "sha": "a4be0028ca56f67f672cb21b4bba8ef0dc792443",
      "author": "Dirk Thomas",
      "author_login": "dirk-thomas",
      "date": "2014-07-11T06:59:40Z",
      "message": "update changelogs"
    },
    {
      "sha": "a4453f3b2892e9aae2097e32f4bd8fc52c9d5d90",
      "author": "Dirk Thomas",
      "author_login": "dirk-thomas",
      "date": "2014-07-07T17:36:31Z",
      "message": "Merge pull request #254 from cottsay/groovy-devel\n\nExport architecture_independent flag in package.xml"
    },
    {
      "sha": "e49f08b9fbc2ac7b35cec1f7ecc209db42816e30",
      "author": "Scott K Logan",
      "author_login": "cottsay",
      "date": "2014-07-03T19:25:42Z",
      "message": "Export architecture_independent flag in package.xml"
    },
    {
      "sha": "480305a1564fcf6108424577ca42de54697593b2",
      "author": "Scott K Logan",
      "author_login": "cottsay",
      "date": "2014-07-02T18:11:11Z",
      "message": "Merge pull request #251 from cottsay/context_menus\n\nrqt_reconfigure: Add context menus for common operations"
    },
    {
      "sha": "f131ba3ecaf3d042c109e2f5b0f45f6911fd136d",
      "author": "Dirk Thomas",
      "author_login": "dirk-thomas",
      "date": "2014-06-29T00:02:33Z",
      "message": "Merge pull request #252 from ros-visualization/topic_statistic_only_if_available\n\nuse TopicStatistics only if available"
    },
    {
      "sha": "2d0b3fb2efcb6c39242195ecd0060cdbc238b1b0",
      "author": "Dirk Thomas",
      "author_login": "dirk-thomas",
      "date": "2014-06-28T23:59:07Z",
      "message": "use TopicStatistics only if available"
    },
    {
      "sha": "42ee8265d4df913c0138d8f2d8ac310258ec240f",
      "author": "Aaron Blasdel",
      "author_login": null,
      "date": "2014-06-27T16:10:01Z",
      "message": "Merge pull request #245 from trainman419/clear_topics\n\nSwitch button usage per #231"
    },
    {
      "sha": "d053ae9850a37ef8e736f7c3d952da1ea1e6c8bd",
      "author": "Aaron Blasdel",
      "author_login": null,
      "date": "2014-06-16T21:10:56Z",
      "message": "Merge pull request #246 from trainman419/plot_all_numeric\n\nMake more things plottable"
    },
    {
      "sha": "7f75b7c307f30c6472384e0e2217d47f632740e4",
      "author": "Aaron Blasdel",
      "author_login": null,
      "date": "2014-06-10T21:06:58Z",
      "message": "Merge pull request #239 from trainman419/rqt_bag_plot\n\nImplement a rqt_bag plotting plugin"
    },
    {
      "sha": "3d127762102df419c888a104493cbaa4d0dfe4ba",
      "author": "trainman419",
      "author_login": "trainman419",
      "date": "2014-05-31T06:38:01Z",
      "message": "Update maintainer status"
    },
    {
      "sha": "70043705c1fb3916227eb83387e1b1482618de47",
      "author": "Aaron Blasdel",
      "author_login": null,
      "date": "2014-06-09T18:24:00Z",
      "message": "Merge pull request #236 from trainman419/py_common_plot\n\nDocument rqt_plot backend as public API"
    },
    {
      "sha": "ef88566174421af5d5dfae119436f465d4800582",
      "author": "Dirk Thomas",
      "author_login": "dirk-thomas",
      "date": "2014-06-02T23:05:59Z",
      "message": "0.3.6"
    },
    {
      "sha": "734bf0d55d3c51c746c29a886e185c073dc33c22",
      "author": "Dirk Thomas",
      "author_login": "dirk-thomas",
      "date": "2014-06-02T23:03:35Z",
      "message": "update changelogs"
    },
    {
      "sha": "6a4004c39692d57056cc8e06fe85c8570045620a",
      "author": "Scott K Logan",
      "author_login": "cottsay",
      "date": "2014-05-21T19:55:34Z",
      "message": "Merge pull request #228 from jbohren-forks/groovy-devel\n\nrqt_reconfigure: Removing unnecessary margins\r\n\r\nThis makes rqt_reconfigure usable on small screens"
    },
    {
      "sha": "7a45a6900758cce7d3ebb4ee7c346813621bebd3",
      "author": "Dirk Thomas",
      "author_login": "dirk-thomas",
      "date": "2014-05-07T22:46:23Z",
      "message": "0.3.5"
    },
    {
      "sha": "6e3126badedf4791fe9c19ae7fca8738a31a91b5",
      "author": "Dirk Thomas",
      "author_login": "dirk-thomas",
      "date": "2014-05-07T22:46:12Z",
      "message": "update changelogs"
    },
    {
      "sha": "e02b50aabc175387d0acf06d4bb6b9878821d041",
      "author": "Dirk Thomas",
      "author_login": "dirk-thomas",
      "date": "2014-05-07T22:32:59Z",
      "message": "Merge pull request #214 from cottsay/rqt-reconfigure-cla\n\nrqt_reconfigure can't take arguments to start of a parameter anymore"
    },
    {
      "sha": "fd8c315629408198ba0dcfec7c145635512f25b0",
      "author": "Dariush Forouher",
      "author_login": "forouher",
      "date": "2014-03-27T13:39:30Z",
      "message": "add displaying of topic/connection statistics along edges\n\nif topic statistics are available (/statistics) then print\nthem along the edges (if in NODE_NODE mode).\n\nDisplayed are\n\n* frequency, delay (based on the header.stamp) and traffic (in kb/s)\n  as text\n* delay again using the color of the edge is an indicator (green to red)\n* traffic using the penwidth of the edge"
    },
    {
      "sha": "88de6365e3d5ea6741b78dd7c381807e3b7f1c26",
      "author": "Dirk Thomas",
      "author_login": "dirk-thomas",
      "date": "2014-04-01T17:18:23Z",
      "message": "Merge pull request #220 from scpeters/catkin_enable_testing\n\nUse CATKIN_ENABLE_TESTING to optionally configure tests"
    },
    {
      "sha": "023c047dffa574cb56852726b1d7a5e2791f482b",
      "author": "Steven Peters",
      "author_login": "scpeters",
      "date": "2014-04-01T06:36:43Z",
      "message": "using CATKIN_ENABLE_TESTING to optionally configure tests"
    },
    {
      "sha": "0b806d6b8deb8dabd26eccaebfb9686b2dcd98de",
      "author": "Dirk Thomas",
      "author_login": "dirk-thomas",
      "date": "2014-01-28T17:20:02Z",
      "message": "0.3.4"
    },
    {
      "sha": "3d056f792997a85ae75002cb4c2743ff15823e2c",
      "author": "Dirk Thomas",
      "author_login": "dirk-thomas",
      "date": "2014-01-28T17:19:45Z",
      "message": "update changelogs"
    },
    {
      "sha": "145f0361e388c7c957fac648d6fbc5f5195db06e",
      "author": "Dirk Thomas",
      "author_login": "dirk-thomas",
      "date": "2014-01-21T19:11:07Z",
      "message": "Merge pull request #204 from hugoe/groovy-devel\n\nrqt_bag: publish clock time from bag"
    },
    {
      "sha": "b18c5a4d37792b38955cb6ea14cbc0f3bd34d6d0",
      "author": "Dirk Thomas",
      "author_login": "dirk-thomas",
      "date": "2014-01-08T23:54:19Z",
      "message": "\"0.3.3\""
    },
    {
      "sha": "817f21dbb4c6b6576dbd1fe2f113eb2998b31c48",
      "author": "Dirk Thomas",
      "author_login": "dirk-thomas",
      "date": "2014-01-08T23:54:10Z",
      "message": "update changelogs"
    },
    {
      "sha": "c78dba5d4040fe6c7b2e1adbf58b4947ae89caab",
      "author": "Dirk Thomas",
      "author_login": "dirk-thomas",
      "date": "2013-11-27T20:59:28Z",
      "message": "add groups for rqt plugins, renamed some plugins (#167)"
    },
    {
      "sha": "7aef1358514dad7436d4cba5d73526d807ad28b5",
      "author": "Dirk Thomas",
      "author_login": "dirk-thomas",
      "date": "2013-10-14T21:35:40Z",
      "message": "0.3.2"
    },
    {
      "sha": "4aea6b529e86efc77408557c3941fd83fc939be6",
      "author": "Dirk Thomas",
      "author_login": "dirk-thomas",
      "date": "2013-10-14T21:35:27Z",
      "message": "update changelogs"
    },
    {
      "sha": "63c57184a5bb09d3fb30fa2ffeb316c3144f3de9",
      "author": "Dirk Thomas",
      "author_login": "dirk-thomas",
      "date": "2013-10-10T00:35:46Z",
      "message": "0.3.1"
    },
    {
      "sha": "0ad5e9d44c3a6d7fd4ab3577e1d643c226ede460",
      "author": "Dirk Thomas",
      "author_login": "dirk-thomas",
      "date": "2013-10-10T00:35:38Z",
      "message": "update changelogs"
    },
    {
      "sha": "e72ec6c19421c7b05fb742c51fa4700dd6a7b82d",
      "author": "Dirk Thomas",
      "author_login": "dirk-thomas",
      "date": "2013-09-29T18:59:00Z",
      "message": "Merge pull request #186 from ros-visualization/rqt_console_rewrite\n\nrewrite of rqt_console"
    },
    {
      "sha": "3597b29cf726fc2db645932c068752de7a5d71ee",
      "author": "Dirk Thomas",
      "author_login": "dirk-thomas",
      "date": "2013-09-26T22:35:51Z",
      "message": "Merge pull request #187 from ros-visualization/change_scrolling_interactive_graphics_view\n\nrqt_graph: changed the method of zooming"
    },
    {
      "sha": "c9a10a6fa38768a170c3e61c45db21bfd8237d23",
      "author": "William Woodall",
      "author_login": "wjwwood",
      "date": "2013-09-26T22:11:43Z",
      "message": "rqt_graph: changed the method of zooming\n\nThis new method handles smaller step sizes. The\ntrackpad on Macbook Pros have a step size which\nranges from +/-2 up to +/-1200, but with a normal\nmouse, in OS X or Linux, the step size is always\n+/-120 or +/-240. This new method scales better\nwith smaller step sizes, making scrolling\nsmoother when using a track pad, which was pretty\nmuch useless before."
    },
    {
      "sha": "8fb5a5ecd7d2968a27e03073f6dc6b47187660e9",
      "author": "Dirk Thomas",
      "author_login": "dirk-thomas",
      "date": "2013-08-29T04:06:57Z",
      "message": "0.3.0"
    },
    {
      "sha": "c586c703450ce1b88880a6ace090f26ff922b2ff",
      "author": "Dirk Thomas",
      "author_login": "dirk-thomas",
      "date": "2013-08-29T04:06:27Z",
      "message": "update changelogs"
    },
    {
      "sha": "eccc18a5020a8c4590d39e82d29344910d025461",
      "author": "Dirk Thomas",
      "author_login": "dirk-thomas",
      "date": "2013-08-20T00:26:10Z",
      "message": "add excplicit icon size for numerous plugins (ros-visualization/rqt#83)"
    },
    {
      "sha": "bdb270d7880f4284f0715f9887f6fa069195b8b5",
      "author": "Isaac Saito",
      "author_login": null,
      "date": "2013-07-15T04:56:03Z",
      "message": "Merge branch 'hydro-devel' into groovy-devel"
    },
    {
      "sha": "1cc801d538bf5cc5eacf785482b23493e6080be9",
      "author": "Isaac Saito",
      "author_login": null,
      "date": "2013-07-10T05:42:59Z",
      "message": "Merge branch 'hydro-devel' into groovy-devel"
    },
    {
      "sha": "217d9ae5f010677074484acf97b92831cc360707",
      "author": "Isaac Saito",
      "author_login": null,
      "date": "2013-07-10T05:13:34Z",
      "message": "0.2.17"
    },
    {
      "sha": "1b4ab7f8c793d197fb08d3c704b9f710f1e9e8a4",
      "author": "Isaac Saito",
      "author_login": null,
      "date": "2013-07-03T18:41:22Z",
      "message": "Correct CHANGELOG.rst by catkin_tag_changelog.\n\nReflect comments to CHANGELOG.rst\n\nAdd release date into hydro in CHANGELOG.rst"
    },
    {
      "sha": "89424dff24d61f667f4d7fc08d278987d7c6596b",
      "author": "Isaac Saito",
      "author_login": null,
      "date": "2013-07-01T17:02:20Z",
      "message": "Adding CHANGELOG.rst"
    },
    {
      "sha": "9bc52ce396b62a206867b3ae6055a224d1aa2246",
      "author": "Dirk Thomas",
      "author_login": "dirk-thomas",
      "date": "2013-06-20T18:10:47Z",
      "message": "Merge pull request #92 from felix-kolbe/groovy-devel\n\nModify checkbox labels and tooltips to be more comprehensible."
    },
    {
      "sha": "2cf6edd4a3a928e05081298a8fd68b07836b9365",
      "author": "Felix Kolbe",
      "author_login": null,
      "date": "2013-06-19T14:46:05Z",
      "message": "Modify checkbox labels and tooltips to be more comprehensible.\n\nAs they were quite confusing what will happen in which checkbox state."
    },
    {
      "sha": "d8871c20a3d14366310c6aefbce4a51ad6266b8c",
      "author": "Isaac Saito",
      "author_login": null,
      "date": "2013-05-06T17:51:08Z",
      "message": "rqt_graph) pkg description updated."
    },
    {
      "sha": "bbef19b05a6ab479913a11989142955a230e5156",
      "author": "Isaac Saito",
      "author_login": null,
      "date": "2013-04-09T20:33:27Z",
      "message": "0.2.16"
    },
    {
      "sha": "7484043c16733fef948437035c49060b19c8efdf",
      "author": "Isaac Saito",
      "author_login": null,
      "date": "2013-04-09T07:02:32Z",
      "message": "0.2.15"
    },
    {
      "sha": "a7846416ddd043ea9836b6f8a552bea8999b477c",
      "author": "Isaac Saito",
      "author_login": "130s",
      "date": "2013-03-14T23:55:34Z",
      "message": "maintainer added to many pkgs"
    },
    {
      "sha": "0e7f419babbb92f8370f7ae949d67923c2a119ba",
      "author": "Isaac Saito",
      "author_login": "130s",
      "date": "2013-03-14T21:59:26Z",
      "message": "0.2.14"
    },
    {
      "sha": "461ea18b236feb317438c11cd13f1d6a5cf84e2c",
      "author": "Isaac Saito",
      "author_login": "130s",
      "date": "2013-03-12T05:14:57Z",
      "message": "0.2.13"
    },
    {
      "sha": "f8f3c758a550528ac80d72591ef3828ed5bcf5ef",
      "author": "Isaac Saito",
      "author_login": null,
      "date": "2013-03-11T20:56:41Z",
      "message": "0.2.12"
    },
    {
      "sha": "f837bea00c324ae668950608d132b18a9d6350eb",
      "author": "Isaac Saito",
      "author_login": "130s",
      "date": "2013-03-08T19:45:50Z",
      "message": "0.2.11"
    },
    {
      "sha": "56aa21504f707361cb1286d84bc10dabee8ba6c4",
      "author": "Aaron Blasdel",
      "author_login": null,
      "date": "2013-01-22T22:26:44Z",
      "message": "0.2.10"
    },
    {
      "sha": "b73692dfe13e84be38165b5cb66c1ca765821392",
      "author": "Isaac Saito",
      "author_login": null,
      "date": "2013-01-20T10:09:18Z",
      "message": "Merge branch 'groovy-devel' of https://github.com/ros-visualization/rqt_common_plugins into groovy-devel"
    },
    {
      "sha": "5743f91d5da46b7ed326d8cc2fc99aa8442e0148",
      "author": "Dirk Thomas",
      "author_login": "dirk-thomas",
      "date": "2013-01-17T23:19:30Z",
      "message": "0.2.9"
    },
    {
      "sha": "bf24b7d6370d5a9cba625a0d84dd65765577063e",
      "author": "Isaac Saito",
      "author_login": null,
      "date": "2013-01-12T22:27:22Z",
      "message": "Merge branch 'groovy-devel' of https://github.com/ros-visualization/rqt_common_plugins into groovy-devel"
    },
    {
      "sha": "33d20bf561c54f6f7387631ed1d2e30f7f234d4b",
      "author": "Dirk Thomas",
      "author_login": "dirk-thomas",
      "date": "2013-01-11T23:08:52Z",
      "message": "0.2.8"
    },
    {
      "sha": "1e367fe811555ab27773bcd358117b30a2d36653",
      "author": "Isaac Saito",
      "author_login": "130s",
      "date": "2013-01-11T09:48:53Z",
      "message": "Merge branch 'groovy-devel' of https://github.com/ros-visualization/rqt_common_plugins into groovy-devel"
    },
    {
      "sha": "74d1df10a59121806c7338a6739454080802feec",
      "author": "Isaac Saito",
      "author_login": "130s",
      "date": "2013-01-10T21:25:32Z",
      "message": "Merge branch 'groovy-devel' of https://github.com/ros-visualization/rqt_common_plugins into groovy-devel"
    },
    {
      "sha": "0f538edb1c20c9cb9b2fcd4a51fd490976d15e70",
      "author": "Isaac Saito",
      "author_login": "130s",
      "date": "2013-01-09T23:06:13Z",
      "message": "Merge branch 'groovy-devel' of https://github.com/ros-visualization/rqt_common_plugins into groovy-devel"
    },
    {
      "sha": "8ab295609f3764f33a514f2cde65caea1e5832d4",
      "author": "Aaron Blasdel",
      "author_login": null,
      "date": "2013-01-08T00:04:09Z",
      "message": "removed incorrect duplicate test_depend entries that are already present in the run_depend entries and added missing run_depend entries on rqt_gui_py"
    },
    {
      "sha": "e02c73a1ffc03af0fa46e8b9f46179a72d029096",
      "author": "Isaac Saito",
      "author_login": "130s",
      "date": "2013-01-03T01:20:33Z",
      "message": "Merge branch 'groovy-devel' of https://github.com/ros-visualization/rqt_common_plugins into groovy-devel"
    },
    {
      "sha": "0098bf118af900f2550317d35c7e6c93d2917927",
      "author": "Dirk Thomas",
      "author_login": "dirk-thomas",
      "date": "2012-12-31T19:26:24Z",
      "message": "update repo urls"
    },
    {
      "sha": "f7621202f232c799723e96af8dceec488d436035",
      "author": "Dirk Thomas",
      "author_login": "dirk-thomas",
      "date": "2012-12-24T21:28:30Z",
      "message": "0.2.7"
    },
    {
      "sha": "699148353948e0459c6dce8063b83f4f0406a451",
      "author": "Dirk Thomas",
      "author_login": "dirk-thomas",
      "date": "2012-12-23T09:56:39Z",
      "message": "0.2.6"
    },
    {
      "sha": "c30bf3013493d177a5b787db7f6b22f034f8a851",
      "author": "Dirk Thomas",
      "author_login": "dirk-thomas",
      "date": "2012-12-22T03:11:45Z",
      "message": "0.2.5"
    },
    {
      "sha": "2db7f97e38164bf581c6eeb8bdb6e939287e32b5",
      "author": "Aaron Blasdel",
      "author_login": null,
      "date": "2012-12-21T17:54:54Z",
      "message": "Merge branch 'groovy-devel' of github.com:ros-visualization/rqt into groovy-devel"
    },
    {
      "sha": "73b0c323d74c45abaccc59766bda1aaa0e34236c",
      "author": "Dirk Thomas",
      "author_login": "dirk-thomas",
      "date": "2012-12-21T09:13:03Z",
      "message": "0.2.4"
    },
    {
      "sha": "dd240bb31f1237d65bb77dac8db3f5c81291eede",
      "author": "Dirk Thomas",
      "author_login": "dirk-thomas",
      "date": "2012-12-21T08:24:46Z",
      "message": "0.2.3"
    },
    {
      "sha": "c52d42a5c488f8bb9ba3e60e3d4761ad4a9abd1b",
      "author": "Dirk Thomas",
      "author_login": "dirk-thomas",
      "date": "2012-12-21T02:29:19Z",
      "message": "0.2.2"
    },
    {
      "sha": "a35e14e544a7a981cc4a753d385a7051fbd943b9",
      "author": "Dirk Thomas",
      "author_login": "dirk-thomas",
      "date": "2012-12-21T01:47:36Z",
      "message": "0.2.1"
    },
    {
      "sha": "cae4e4f5a24a863dc82e9ce66e673872fa1e1f69",
      "author": "Dirk Thomas",
      "author_login": "dirk-thomas",
      "date": "2012-12-21T01:39:05Z",
      "message": "0.2.0"
    },
    {
      "sha": "8b38db18d0a7b556d6a58292596047b8cc402039",
      "author": "Aaron Blasdel",
      "author_login": null,
      "date": "2012-12-20T17:18:33Z",
      "message": "catkinize shell scripts and removed load_manifest calls"
    },
    {
      "sha": "2bb99649b801c62168ab9079cd78adeb1d00fb97",
      "author": "Dirk Thomas",
      "author_login": "dirk-thomas",
      "date": "2012-12-20T04:12:55Z",
      "message": "Merge pull request #61 from ros-visualization/catkinize\n\ncatkinizing"
    },
    {
      "sha": "8ae059ecf1245beea7eb53aba166e241dff075a2",
      "author": "Aaron Blasdel",
      "author_login": null,
      "date": "2012-12-18T00:38:25Z",
      "message": "catkinizing\n\ncatkinize: remaining uncatkinized packages\n\ncatkinize: removed rqt stack\n\ncatkinize: removing Makefiles\n\ncatkinize: added version tags\n\ncatkinize: fixed version numbers\n\ncatkinize: added setup.py files\n\ncatkinize: added setup.py files\n\ncatkinize: fixed cmake lists\n\ncatkinize: removed rosdeps\n\ncatkinize: building\n\ncatkinize: added setup.py files\n\ncatkinize: move plugin.xmls\n\ncatkinize: add qt_gui depend\n\ncatkinize: added repositories\n\nfix deps\n\nadd .gitignore\n\nfix export tag in rqt_gui_py\n\nadd missing target_link_libraries\n\ncatkinize: rqt_msg, rqt_bag, rqt_console, rqt_bag_plugins now work in install space\n\ncatkinize: all python plugins run from their scripts in install space\n\nrqt_nav_view: Removed extra plugin install rule.\n\ndisable graying out unavailable python plugins\n\ncatkinize: c++ plugins working, rosruning working in install/build spaces\n\ncatkinize: removed rosmake style .gitignore files\n\ncatkinize: fixed the \"s\"\n\nadd missing inc dirs"
    },
    {
      "sha": "5bb70e067071150be83154db6fc47769320d11ac",
      "author": "Aaron Blasdel",
      "author_login": null,
      "date": "2012-12-06T03:19:10Z",
      "message": "rqt: conversion of scripts to new qt_gui standalone package argument system"
    },
    {
      "sha": "aada6102f7b52648473d5b3e4c64eebd421771b9",
      "author": "Aaron Blasdel",
      "author_login": null,
      "date": "2012-12-05T20:36:01Z",
      "message": "rqt: fix for standalone scripts to allow for standalone arguments"
    },
    {
      "sha": "91fddee9c2e6864cadd4f0fc48b4f191b9d853d4",
      "author": "Dirk Thomas",
      "author_login": "dirk-thomas",
      "date": "2012-12-04T00:04:15Z",
      "message": "Merge pull request #40 from stonier/patch-1\n\nBackground colour for the scene"
    },
    {
      "sha": "232796c028acbf701a6002e036a09ca90b507c58",
      "author": "Daniel Stonier",
      "author_login": "stonier",
      "date": "2012-12-03T23:40:08Z",
      "message": "Background colour for the scene\n\nThe ros graph plugin shows up badly in dark coloured qt themes (black ellipses on a dark background).\r\n\r\nI usually don't like forcing colours in an themed application, but in a rendered scene, your theme doesn't have a choice over the colours of the components (black ellipses for the nodes, etc), so it's choice of matching background is often wrong. This helps with that."
    },
    {
      "sha": "c79e48d057c00658f320a3234b301ded9f7f5125",
      "author": "Aaron Blasdel",
      "author_login": null,
      "date": "2012-12-03T21:36:10Z",
      "message": "rqt: script overhaul for running plugins in standalone mode"
    },
    {
      "sha": "21d984f354a79172282da480735ec3a43f395b17",
      "author": "Dirk Thomas",
      "author_login": "dirk-thomas",
      "date": "2012-11-30T22:09:43Z",
      "message": "more code style"
    },
    {
      "sha": "81432378044fa3123a27b6228f1cb4e3b1ee96ee",
      "author": "Dorian Scholz",
      "author_login": "DorianScholz",
      "date": "2012-11-22T11:52:06Z",
      "message": "rqt_graph: fixed issue #23"
    },
    {
      "sha": "e8cad85297f7eb1094f94288db00aedfad0d9662",
      "author": "Aaron Blasdel",
      "author_login": null,
      "date": "2012-11-09T02:31:22Z",
      "message": "rqt_various: fixed PySide specific errors"
    },
    {
      "sha": "f4f32a70cd3a36f46e6300a79c779d3e436961a2",
      "author": "Aaron Blasdel",
      "author_login": null,
      "date": "2012-09-18T22:37:21Z",
      "message": "Merge branch 'master' of https://kforge.ros.org/visualization/rqt"
    },
    {
      "sha": "142b76c2c60f766aad3b96c330c00594bb8397ef",
      "author": "Dorian Scholz",
      "author_login": "DorianScholz",
      "date": "2012-09-15T11:04:47Z",
      "message": "changed import style for Qt modules to use python_qt_binding directly"
    },
    {
      "sha": "8fd04e0cb5e2cc25672cbb7815b8821d79b6d7cb",
      "author": "Dorian Scholz",
      "author_login": "DorianScholz",
      "date": "2012-09-14T16:42:57Z",
      "message": "Merge remote-tracking branch 'origin/master'\n\nConflicts:\n\trqt_bag/src/rqt_bag/bag_timeline.py\n\trqt_bag/src/rqt_bag/bag_widget.py\n\trqt_bag_plugins/src/rqt_bag_plugins/image_view.py"
    },
    {
      "sha": "4a72065dcebdab6b3310fb3f20baa9991025b19c",
      "author": "Dorian Scholz",
      "author_login": "DorianScholz",
      "date": "2012-09-14T14:02:35Z",
      "message": "adapted qt imports to new qt_binding_helper"
    },
    {
      "sha": "34a48d104b5229bf5f1844a81e4ac419a17b0c2f",
      "author": "Dirk Thomas",
      "author_login": "dirk-thomas",
      "date": "2012-07-18T02:41:54Z",
      "message": "removed qt_gui_core, moved rqt to root"
    },
    {
      "sha": "66e68fb3a4ba10b99d2c6c8bc9ebdcf1cf0650ca",
      "author": "Dirk Thomas",
      "author_login": "dirk-thomas",
      "date": "2012-07-17T17:28:52Z",
      "message": "catch exception instance with as instead of comma for Pzthon 3.x compatibility"
    },
    {
      "sha": "dcb7b981187d470fcc052817d400c93df6403db9",
      "author": "Thibault Kruse",
      "author_login": null,
      "date": "2012-07-05T20:24:46Z",
      "message": "enhancement ticket Ticket #5469: enable 'make test' target for rqt stack and packages"
    },
    {
      "sha": "25fae9c4e827d87c4fc98ca0d9b17f6242a370b2",
      "author": "Dirk Thomas",
      "author_login": "dirk-thomas",
      "date": "2012-06-25T19:20:08Z",
      "message": "code formatting according to pep8"
    },
    {
      "sha": "be7e8a4aa4b1f8498ea83513a8a23dc94a915113",
      "author": "Dirk Thomas",
      "author_login": "dirk-thomas",
      "date": "2012-06-24T23:03:28Z",
      "message": "modified some rqt plugins to inherit from rqt_gui_py Plugin"
    },
    {
      "sha": "f19cdc51175bd8ff78dcde96e235aad1d670c1c5",
      "author": "Dirk Thomas",
      "author_login": "dirk-thomas",
      "date": "2012-06-24T22:47:12Z",
      "message": "code formatting according to pep8"
    },
    {
      "sha": "7dc6039404b4f92761ff85c7101db4ec17a63c5d",
      "author": "Dirk Thomas",
      "author_login": "dirk-thomas",
      "date": "2012-06-24T22:39:43Z",
      "message": "code formatting according to pep8"
    },
    {
      "sha": "74efd267ecc37bc59646769519f1af507497d897",
      "author": "Thibault Kruse",
      "author_login": null,
      "date": "2012-06-20T13:58:43Z",
      "message": "options moved to second ui row"
    },
    {
      "sha": "d1a5fcad1c37a47d08611b8f8a47d914f5363a15",
      "author": "Thibault Kruse",
      "author_login": null,
      "date": "2012-06-18T14:42:01Z",
      "message": "treating edges with same labels as siblings as a parameter"
    },
    {
      "sha": "ea1639d65c72a721ddff99107244624168eb3d62",
      "author": "Thibault Kruse",
      "author_login": null,
      "date": "2012-06-18T21:40:01Z",
      "message": "fixed unit tests after code moved"
    },
    {
      "sha": "25bac62a87e3b37d72f89b683552c38f43e7ec3c",
      "author": "Dirk Thomas",
      "author_login": "dirk-thomas",
      "date": "2012-06-11T22:20:57Z",
      "message": "replaced argument names for save/restore settings of a plugin"
    },
    {
      "sha": "27f3b2af45952c674a4b756b60ffff4aa2e2e2af",
      "author": "Dirk Thomas",
      "author_login": "dirk-thomas",
      "date": "2012-06-10T22:47:01Z",
      "message": "modified tag name in qtgui plugin manifest"
    },
    {
      "sha": "f7f6706a9745eea071e9fc0f0861ed1baa1e848a",
      "author": "Dirk Thomas",
      "author_login": "dirk-thomas",
      "date": "2012-06-10T22:41:40Z",
      "message": "modified semantic of plugin manifest, renamed file names according to PEP 8, refactored relative imports according to PEP 328"
    },
    {
      "sha": "a226b1bcdf77b4f44e95aff493fdfd17cf613944",
      "author": "Dirk Thomas",
      "author_login": "dirk-thomas",
      "date": "2012-06-05T22:21:35Z",
      "message": "major renaming and refactoring of all packages"
    },
    {
      "sha": "7d4533b91f6f1572c3364a7d999d7446a91ce5b9",
      "author": "Dirk Thomas",
      "author_login": "dirk-thomas",
      "date": "2012-05-31T05:50:36Z",
      "message": "renamed packages and moved into separate stacks (refactoring not yet completed)"
    },
    {
      "sha": "6f6f9208f1e88e67f66c2e5f6b119f82a84e9ae2",
      "author": "Dirk Thomas",
      "author_login": "dirk-thomas",
      "date": "2011-10-01T10:16:18Z",
      "message": "added yet empty ros_gui stack"
    }
  ]
}